README.md
setup.cfg
setup.py
dbsession/__init__.py
dbsession/dbsession.py
dbsession.egg-info/PKG-INFO
dbsession.egg-info/SOURCES.txt
dbsession.egg-info/dependency_links.txt
dbsession.egg-info/top_level.txt
example/A.py
example/__init__.py
example/__main__.py
example/config.py
example/modules/A.py
example/modules/B.py
example/modules/__init__.py