Metadata-Version: 2.1
Name: dbsession
Version: 0.6.3
Summary: The python postgreSQL ORM
Home-page: https://github.com/treble-ai/dbsession
Author: imwiwiim90
Author-email: imwiwiim90@gmail.com
License: MIT
Keywords: python,postgreSQL,ORM,psycopg2
Platform: UNKNOWN
Classifier: Development Status :: 4 - Beta
Classifier: Intended Audience :: Developers
Classifier: Topic :: Software Development :: Build Tools
Classifier: License :: OSI Approved :: MIT License
Classifier: Programming Language :: Python :: 3.5
Classifier: Programming Language :: Python :: 3.6
Classifier: Programming Language :: Python :: 3.7
Classifier: Programming Language :: Python :: 3.8
